logust-0.2.1.dist-info/METADATA
logust-0.2.1.dist-info/WHEEL
logust-0.2.1.dist-info/licenses/LICENSE
logust/__init__.py
logust/_logger.py
logust/_logust.cpython-311-darwin.so
logust/_logust.pyi
logust/_opt.py
logust/_parse.py
logust/_template.py
logust/_traceback.py
logust/_types.py
logust/contrib/__init__.py
logust/contrib/decorators.py
logust/contrib/logging_handler.py
logust/contrib/starlette.py
logust/py.typed
logust-0.2.1.dist-info/RECORD
