Metadata-Version: 2.4
Name: logust
Version: 0.2.1
Classifier: Development Status :: 4 - Beta
Classifier: Intended Audience :: Developers
Classifier: License :: OSI Approved :: MIT License
Classifier: Operating System :: OS Independent
Classifier: Programming Language :: Python :: 3
Classifier: Programming Language :: Python :: 3.10
Classifier: Programming Language :: Python :: 3.11
Classifier: Programming Language :: Python :: 3.12
Classifier: Programming Language :: Python :: 3.13
Classifier: Programming Language :: Python :: 3.14
Classifier: Programming Language :: Rust
Classifier: Programming Language :: Python :: Implementation :: CPython
Classifier: Programming Language :: Python :: Implementation :: PyPy
Classifier: Topic :: System :: Logging
Classifier: Typing :: Typed
Requires-Dist: mypy>=1.0 ; extra == 'dev'
Requires-Dist: pre-commit>=4.0 ; extra == 'dev'
Requires-Dist: ruff>=0.8 ; extra == 'dev'
Requires-Dist: pytest>=8.0 ; extra == 'test'
Requires-Dist: pytest-cov>=4.0 ; extra == 'test'
Requires-Dist: loguru>=0.7 ; extra == 'bench'
Requires-Dist: mkdocs-material>=9.5 ; extra == 'docs'
Requires-Dist: mkdocstrings[python]>=0.24 ; extra == 'docs'
Requires-Dist: mkdocs-minify-plugin>=0.8 ; extra == 'docs'
Provides-Extra: dev
Provides-Extra: test
Provides-Extra: bench
Provides-Extra: docs
License-File: LICENSE
Summary: A fast, Rust-powered Python logging library inspired by loguru
Keywords: logging,logger,rust,performance,loguru
Author: yamaaaaaa31
License: MIT
Requires-Python: >=3.10
Project-URL: Homepage, https://github.com/yamaaaaaa31/logust
Project-URL: Repository, https://github.com/yamaaaaaa31/logust
Project-URL: Issues, https://github.com/yamaaaaaa31/logust/issues
